<annotation>
	<folder>train</folder>
	<filename>scaled_20200816_183647.jpg</filename>
	<path>C:\Users\Pedro\Desktop\cartas\single_card\facil mais novo\train\scaled_20200816_183647.jpg</path>
	<source>
		<database>Unknown</database>
	</source>
	<size>
		<width>378</width>
		<height>504</height>
		<depth>3</depth>
	</size>
	<segmented>0</segmented>
	<object>
		<name>king</name>
		<pose>Unspecified</pose>
		<truncated>0</truncated>
		<difficult>0</difficult>
		<bndbox>
			<xmin>133</xmin>
			<ymin>300</ymin>
			<xmax>239</xmax>
			<ymax>423</ymax>
		</bndbox>
	</object>
</annotation>
