<annotation>
	<folder>fotos</folder>
	<filename>scaled_20200816_115414.jpg</filename>
	<path>C:\Users\Pedro\Desktop\cartas\single_card\facil mais novo\fotos\scaled_20200816_115414.jpg</path>
	<source>
		<database>Unknown</database>
	</source>
	<size>
		<width>378</width>
		<height>504</height>
		<depth>3</depth>
	</size>
	<segmented>0</segmented>
	<object>
		<name>nine</name>
		<pose>Unspecified</pose>
		<truncated>0</truncated>
		<difficult>0</difficult>
		<bndbox>
			<xmin>25</xmin>
			<ymin>41</ymin>
			<xmax>299</xmax>
			<ymax>419</ymax>
		</bndbox>
	</object>
</annotation>
